[
  {
    "meridian_name": "Stomach (ST)",
    "point_number": "ST1",
    "korean_name": "승읍",
    "romanized_korean": "Seung Eub",
    "english_translation": "Contains Tears",
    "anatomical_location": "Directly below the pupil, between eyeball and infraorbital ridge",
    "healing_function": "Benefits eyes, stops lacrimation, treats redness/swelling",
    "martial_application": "Causes disorientation and visual disruption",
    "shared_name_indicator": null,
    "bilateral": "Yes"
  },
  {
    "meridian_name": "Stomach (ST)",
    "point_number": "ST2",
    "korean_name": "사백",
    "romanized_korean": "Sah Baek",
    "english_translation": "Four Whites",
    "anatomical_location": "Directly below ST1 in depression of infraorbital foramen",
    "healing_function": "Clears vision, relieves facial pain and twitching",
    "martial_application": "Pain point, disrupts visual processing",
    "shared_name_indicator": null,
    "bilateral": "Yes"
  },
  {
    "meridian_name": "Stomach (ST)",
    "point_number": "ST3",
    "korean_name": "거료",
    "romanized_korean": "Kuh Ryoh",
    "english_translation": "Great Seam",
    "anatomical_location": "Below ST2, level with nostril, directly below pupil",
    "healing_function": "Relieves facial paralysis and twitching",
    "martial_application": "Facial strike, disrupts breathing or balance",
    "shared_name_indicator": null,
    "bilateral": "Yes"
  },
  {
    "meridian_name": "Stomach (ST)",
    "point_number": "ST4",
    "korean_name": "지창",
    "romanized_korean": "Jee Chahng",
    "english_translation": "Terrestrial Granary",
    "anatomical_location": "0.4 cun lateral to corner of mouth",
    "healing_function": "Treats deviation of mouth, activates meridian",
    "martial_application": "Pain point on jaw, can stun or distract",
    "shared_name_indicator": null,
    "bilateral": "Yes"
  },
  {
    "meridian_name": "Stomach (ST)",
    "point_number": "ST5",
    "korean_name": "대영",
    "romanized_korean": "Dae Yuhng",
    "english_translation": "Big Welcome",
    "anatomical_location": "Anterior to angle of mandible, on masseter muscle",
    "healing_function": "Eliminates wind, reduces swelling of jaw",
    "martial_application": "Weakens jaw, causes intense localized pain",
    "shared_name_indicator": null,
    "bilateral": "Yes"
  },
  {
    "meridian_name": "Stomach (ST)",
    "point_number": "ST6",
    "korean_name": "협거",
    "romanized_korean": "Hyuhp Guh",
    "english_translation": "Jaw Vehicle",
    "anatomical_location": "One finger breadth anterior and superior to angle of mandible at belly of masseter, clench teeth to locate",
    "healing_function": "Eliminates wind, benefits jaw and teeth, activates channel",
    "martial_application": "Striking disrupts jaw function and can cause knockdown from nerve trauma",
    "shared_name_indicator": null,
    "bilateral": "Yes"
  },
  {
    "meridian_name": "Stomach (ST)",
    "point_number": "ST7",
    "korean_name": "하관",
    "romanized_korean": "Hah Gwahn",
    "english_translation": "Lower Hinge",
    "anatomical_location": "In depression anterior to condyloid process of mandible, at lower border of zygomatic arch",
    "healing_function": "Benefits ears, jaw, and teeth; relieves pain and spasms",
    "martial_application": "Can disrupt hearing and jaw motion, used to cause intense disorientation",
    "shared_name_indicator": null,
    "bilateral": "Yes"
  },
  {
    "meridian_name": "Stomach (ST)",
    "point_number": "ST8",
    "korean_name": "두유",
    "romanized_korean": "Doo Yoo",
    "english_translation": "Head’s Support",
    "anatomical_location": "At corner of forehead, 0.5 cun above anterior hairline and 4.5 cun lateral to midline",
    "healing_function": "Clears heat, alleviates headache, benefits eyes",
    "martial_application": "Causes dizziness or blackout when struck, disrupts visual clarity",
    "shared_name_indicator": null,
    "bilateral": "Yes"
  },
  {
    "meridian_name": "Stomach (ST)",
    "point_number": "ST9",
    "korean_name": "인영",
    "romanized_korean": "In Yuhng",
    "english_translation": "Man’s Welcome",
    "anatomical_location": "Level with tip of Adam’s apple, on anterior border of SCM, next to carotid artery",
    "healing_function": "Regulates Qi and blood, lowers hypertension, benefits throat",
    "martial_application": "Severe strike can cause blackout or death due to arterial trauma",
    "shared_name_indicator": null,
    "bilateral": "Yes"
  },
  {
    "meridian_name": "Stomach (ST)",
    "point_number": "ST10",
    "korean_name": "수돌",
    "romanized_korean": "Soo Dohl",
    "english_translation": "Foutain",
    "anatomical_location": "Midway between ST9 and ST11 at anterior border of SCM",
    "healing_function": "Benefits throat and voice, disperses stagnation in neck",
    "martial_application": "Can bruise or paralyze neck, disrupts breathing when pressed or struck",
    "shared_name_indicator": null,
    "bilateral": "Yes"
  },
  {
    "meridian_name": "Stomach (ST)",
    "point_number": "ST11",
    "korean_name": "기사",
    "romanized_korean": "Kee Sah",
    "english_translation": "Ki's Residence",
    "anatomical_location": "At superior border of medial end of clavicle, between sternal and clavicular heads of SCM",
    "healing_function": "Regulates Qi, benefits throat and chest",
    "martial_application": "Pressing here can cause choking or breath loss, used in restraint techniques",
    "shared_name_indicator": null,
    "bilateral": "Yes"
  },
  {
    "meridian_name": "Stomach (ST)",
    "point_number": "ST12",
    "korean_name": "결분",
    "romanized_korean": "Kyuhl Boon",
    "english_translation": "Empty Basin",
    "anatomical_location": "In supraclavicular fossa, 4 cun lateral to midline",
    "healing_function": "Disperses and descends lung Qi, clears heat from chest",
    "martial_application": "Can shock lungs or diaphragm when struck or compressed",
    "shared_name_indicator": null,
    "bilateral": "Yes"
  },
  {
    "meridian_name": "Stomach (ST)",
    "point_number": "ST13",
    "korean_name": "기호",
    "romanized_korean": "Kee Hoh",
    "english_translation": "Ki's Household",
    "anatomical_location": "Below clavicle, 4 cun lateral to midline in first intercostal space",
    "healing_function": "Unbinds chest, alleviates cough and asthma",
    "martial_application": "Strike can impair breathing or cause severe chest pain",
    "shared_name_indicator": null,
    "bilateral": "Yes"
  },
  {
    "meridian_name": "Stomach (ST)",
    "point_number": "ST14",
    "korean_name": "고방",
    "romanized_korean": "Koh Bahng",
    "english_translation": "Storehouse",
    "anatomical_location": "In second intercostal space, 4 cun lateral to midline",
    "healing_function": "Relieves chest congestion and pain, opens lungs",
    "martial_application": "Blow here disrupts respiration, can cause rib injury",
    "shared_name_indicator": null,
    "bilateral": "Yes"
  },
  {
    "meridian_name": "Stomach (ST)",
    "point_number": "ST15",
    "korean_name": "옥예",
    "romanized_korean": "Ohg Yea",
    "english_translation": "Room Screen",
    "anatomical_location": "In third intercostal space, 4 cun lateral to midline",
    "healing_function": "Alleviates chest pain, clears lung heat, calms spirit",
    "martial_application": "Strike disrupts breathing and can affect heart rhythm",
    "shared_name_indicator": null,
    "bilateral": "Yes"
  },
  {
    "meridian_name": "Stomach (ST)",
    "point_number": "ST16",
    "korean_name": "응창",
    "romanized_korean": "Eung Chang",
    "english_translation": "Breast’s Window",
    "anatomical_location": "In fourth intercostal space, 4 cun lateral to midline",
    "healing_function": "Benefits breasts, regulates Qi in chest",
    "martial_application": "Painful chest cavity point, can stun or drop opponent",
    "shared_name_indicator": null,
    "bilateral": "Yes"
  },
  {
    "meridian_name": "Stomach (ST)",
    "point_number": "ST17",
    "korean_name": "유중",
    "romanized_korean": "Yoo Joong",
    "english_translation": "Middle of Breast",
    "anatomical_location": "At center of nipple (used as anatomical landmark, not needled)",
    "healing_function": "Reference point for anatomical orientation",
    "martial_application": "Sensitive target area; impacts ribs and lungs if struck",
    "shared_name_indicator": null,
    "bilateral": "Yes"
  },
  {
    "meridian_name": "Stomach (ST)",
    "point_number": "ST18",
    "korean_name": "유근",
    "romanized_korean": "Yoo Geun",
    "english_translation": "Breast Root",
    "anatomical_location": "Directly below nipple in fifth intercostal space",
    "healing_function": "Clears stagnation, benefits breasts and chest",
    "martial_application": "Impact causes severe pain, disrupts lung and heart rhythm",
    "shared_name_indicator": null,
    "bilateral": "Yes"
  },
  {
    "meridian_name": "Stomach (ST)",
    "point_number": "ST19",
    "korean_name": "불용",
    "romanized_korean": "Bool Yohng",
    "english_translation": "Uncontainable",
    "anatomical_location": "6 cun above umbilicus, 2 cun lateral to midline",
    "healing_function": "Harmonizes stomach, descends rebellious Qi",
    "martial_application": "Striking may cause digestive disruption or solar plexus trauma",
    "shared_name_indicator": null,
    "bilateral": "Yes"
  },
  {
    "meridian_name": "Stomach (ST)",
    "point_number": "ST20",
    "korean_name": "승만",
    "romanized_korean": "Seung Mahn",
    "english_translation": "Support Fullness",
    "anatomical_location": "5 cun above umbilicus, 2 cun lateral to midline",
    "healing_function": "Regulates middle burner, relieves abdominal fullness",
    "martial_application": "Causes cramping, digestive pain, or breath disruption",
    "shared_name_indicator": null,
    "bilateral": "Yes"
  },
  {
    "meridian_name": "Stomach (ST)",
    "point_number": "ST21",
    "korean_name": "량문",
    "romanized_korean": "Yahng Moon",
    "english_translation": "Beam Gate",
    "anatomical_location": "4 cun above umbilicus, 2 cun lateral to midline",
    "healing_function": "Transforms stagnation, stops vomiting, harmonizes ST",
    "martial_application": "Strike can stun diaphragm or cause vomiting",
    "shared_name_indicator": null,
    "bilateral": "Yes"
  },
  {
    "meridian_name": "Stomach (ST)",
    "point_number": "ST22",
    "korean_name": "관문",
    "romanized_korean": "Gwahn Moon",
    "english_translation": "Pass Gate",
    "anatomical_location": "3 cun above umbilicus, 2 cun lateral to midline",
    "healing_function": "Regulates intestines and benefits urination",
    "martial_application": "Blow can disrupt bladder or bowel control",
    "shared_name_indicator": null,
    "bilateral": "Yes"
  },
  {
    "meridian_name": "Stomach (ST)",
    "point_number": "ST23",
    "korean_name": "태을",
    "romanized_korean": "Tae Eul",
    "english_translation": "Supreme Unity",
    "anatomical_location": "2 cun above umbilicus, 2 cun lateral to midline",
    "healing_function": "Calms spirit, harmonizes middle Jiao",
    "martial_application": "Blow disrupts digestion and can weaken centerline",
    "shared_name_indicator": null,
    "bilateral": "Yes"
  },
  {
    "meridian_name": "Stomach (ST)",
    "point_number": "ST24",
    "korean_name": "화개",
    "romanized_korean": "Hwahl Yook Moon",
    "english_translation": "Door of Slippery Flesh",
    "anatomical_location": "1 cun above umbilicus, 2 cun lateral to midline",
    "healing_function": "Transforms phlegm, calms mind",
    "martial_application": "Painful if struck; pressure can cause nausea or spasm",
    "shared_name_indicator": null,
    "bilateral": "Yes"
  },
  {
    "meridian_name": "Stomach (ST)",
    "point_number": "ST25",
    "korean_name": "천추",
    "romanized_korean": "Chuhn Choo",
    "english_translation": "Celestial Pivot",
    "anatomical_location": "Level with umbilicus, 2 cun lateral to midline",
    "healing_function": "Regulates intestines, resolves dampness and heat",
    "martial_application": "Vital strike to abdomen, can cause knockout or nausea",
    "shared_name_indicator": null,
    "bilateral": "Yes"
  },
  {
    "meridian_name": "Stomach (ST)",
    "point_number": "ST26",
    "korean_name": "외릉",
    "romanized_korean": "Wae Reung",
    "english_translation": "Outer Tomb",
    "anatomical_location": "1 cun below umbilicus, 2 cun lateral to midline",
    "healing_function": "Regulates intestines, relieves abdominal pain",
    "martial_application": "Strike can paralyze or cramp lower abdomen",
    "shared_name_indicator": null,
    "bilateral": "Yes"
  },
  {
    "meridian_name": "Stomach (ST)",
    "point_number": "ST27",
    "korean_name": "대거",
    "romanized_korean": "Dae Guh",
    "english_translation": "The Great ",
    "anatomical_location": "2 cun below umbilicus, 2 cun lateral to midline",
    "healing_function": "Benefits kidney and essence, promotes urination",
    "martial_application": "Sensitive lower abdominal target, disrupts energy flow",
    "shared_name_indicator": null,
    "bilateral": "Yes"
  },
  {
    "meridian_name": "Stomach (ST)",
    "point_number": "ST28",
    "korean_name": "수도",
    "romanized_korean": "Soo Doh",
    "english_translation": "Waterway",
    "anatomical_location": "3 cun below umbilicus, 2 cun lateral to midline",
    "healing_function": "Regulates lower burner, benefits bladder and uterus",
    "martial_application": "Disrupts reproductive or bladder function when struck",
    "shared_name_indicator": null,
    "bilateral": "Yes"
  },
  {
    "meridian_name": "Stomach (ST)",
    "point_number": "ST29",
    "korean_name": "귀래",
    "romanized_korean": "Kee Rae",
    "english_translation": "Returning Ki",
    "anatomical_location": "4 cun below umbilicus, 2 cun lateral to midline",
    "healing_function": "Warms lower burner, regulates menstruation",
    "martial_application": "Impact can cause collapse or intense abdominal pain",
    "shared_name_indicator": null,
    "bilateral": "Yes"
  },
  {
    "meridian_name": "Stomach (ST)",
    "point_number": "ST30",
    "korean_name": "기충",
    "romanized_korean": "Kee Choong ",
    "english_translation": "Pouring Ki",
    "anatomical_location": "5 cun below umbilicus, 2 cun lateral to midline",
    "healing_function": "Regulates Qi in lower Jiao, nourishes sea of food",
    "martial_application": "Powerful knockout point, can affect whole body if struck",
    "shared_name_indicator": null,
    "bilateral": "Yes"
  },
  {
    "meridian_name": "Stomach (ST)",
    "point_number": "ST31",
    "korean_name": "비관",
    "romanized_korean": "Bee Gwahn",
    "english_translation": "Hip's Hinge",
    "anatomical_location": "At junction of lateral 1/3 and medial 2/3 of line between ASIS and superior lateral border of patella",
    "healing_function": "Activates channel, relieves leg pain and weakness",
    "martial_application": "Can deaden leg movement or cause paralysis if struck",
    "shared_name_indicator": null,
    "bilateral": "Yes"
  },
  {
    "meridian_name": "Stomach (ST)",
    "point_number": "ST32",
    "korean_name": "복토",
    "romanized_korean": "Bohk Toh",
    "english_translation": "Hidden Rabbit",
    "anatomical_location": "6 cun above lateral-superior border of patella, on line between ST31 and ST32",
    "healing_function": "Alleviates leg and knee pain, disperses wind",
    "martial_application": "Painful muscle point, weakens leg and causes numbness",
    "shared_name_indicator": null,
    "bilateral": "Yes"
  },
  {
    "meridian_name": "Stomach (ST)",
    "point_number": "ST33",
    "korean_name": "음시",
    "romanized_korean": "Eum Shee",
    "english_translation": "Yin Market",
    "anatomical_location": "3 cun above superior border of patella, on line with ASIS",
    "healing_function": "Dispels wind-damp, benefits knee joint",
    "martial_application": "Affects balance and leg structure, used to drop an opponent",
    "shared_name_indicator": null,
    "bilateral": "Yes"
  },
  {
    "meridian_name": "Stomach (ST)",
    "point_number": "ST34",
    "korean_name": "양구",
    "romanized_korean": "Yang Goo",
    "english_translation": "Ridge Mound",
    "anatomical_location": "2 cun above superior lateral border of patella",
    "healing_function": "Moderates acute conditions, benefits knee",
    "martial_application": "Sensitive strike point, weakens knee structure",
    "shared_name_indicator": null,
    "bilateral": "Yes"
  },
  {
    "meridian_name": "Stomach (ST)",
    "point_number": "ST35",
    "korean_name": "독비",
    "romanized_korean": "Dohk Bi",
    "english_translation": "Calf’s Nose",
    "anatomical_location": "In depression lateral to patellar ligament when knee is flexed",
    "healing_function": "Dispels wind-damp, reduces swelling in knee",
    "martial_application": "Primary target for disabling knee, very painful when struck",
    "shared_name_indicator": null,
    "bilateral": "Yes"
  },
  {
    "meridian_name": "Stomach (ST)",
    "point_number": "ST36",
    "korean_name": "족삼리",
    "romanized_korean": "Johk Sahm Ri",
    "english_translation": "Leg Three Measures",
    "anatomical_location": "3 cun below ST35, one finger breadth lateral to anterior crest of tibia",
    "healing_function": "Boosts immunity, regulates digestion and Qi",
    "martial_application": "Paralyzes leg temporarily when struck, disrupts energy",
    "shared_name_indicator": null,
    "bilateral": "Yes"
  },
  {
    "meridian_name": "Stomach (ST)",
    "point_number": "ST37",
    "korean_name": "상거허",
    "romanized_korean": "Sahng Guh Huh",
    "english_translation": "Upper Void",
    "anatomical_location": "6 cun below ST35, one finger breadth from tibia",
    "healing_function": "Regulates intestines, clears damp heat",
    "martial_application": "Painful deep muscle point, disturbs balance when struck",
    "shared_name_indicator": null,
    "bilateral": "Yes"
  },
  {
    "meridian_name": "Stomach (ST)",
    "point_number": "ST38",
    "korean_name": "조구",
    "romanized_korean": "Joh Goo",
    "english_translation": "Lines Opening",
    "anatomical_location": "8 cun below ST35, midway between ST35 and ST41",
    "healing_function": "Benefits shoulder, relieves pain in joints",
    "martial_application": "Weakens arm and shoulder when struck on leg",
    "shared_name_indicator": null,
    "bilateral": "Yes"
  },
  {
    "meridian_name": "Stomach (ST)",
    "point_number": "ST39",
    "korean_name": "하거허",
    "romanized_korean": "Hah Guh Huh",
    "english_translation": "Lower Void",
    "anatomical_location": "9 cun below ST35, one finger breadth from tibia",
    "healing_function": "Regulates small intestine, clears damp-heat",
    "martial_application": "Strike disables leg function and disrupts digestion",
    "shared_name_indicator": null,
    "bilateral": "Yes"
  },
  {
    "meridian_name": "Stomach (ST)",
    "point_number": "ST40",
    "korean_name": "풍륭",
    "romanized_korean": "Poong Nyoong",
    "english_translation": "Abundance & Prosperity",
    "anatomical_location": "8 cun superior to lateral malleolus, two finger breadths lateral to ST38",
    "healing_function": "Transforms phlegm, clears chest congestion",
    "martial_application": "Disrupts balance and causes pain throughout body",
    "shared_name_indicator": null,
    "bilateral": "Yes"
  },
  {
    "meridian_name": "Stomach (ST)",
    "point_number": "ST41",
    "korean_name": "해계",
    "romanized_korean": "Hae Gyea",
    "english_translation": "Release the Stream",
    "anatomical_location": "On dorsum of foot at midpoint of transverse crease of ankle joint",
    "healing_function": "Clears heat from stomach, calms spirit",
    "martial_application": "Affects ankle joint, disrupts mobility",
    "shared_name_indicator": null,
    "bilateral": "Yes"
  },
  {
    "meridian_name": "Stomach (ST)",
    "point_number": "ST42",
    "korean_name": "충양",
    "romanized_korean": "Choong Yahng",
    "english_translation": "Pouring Yang",
    "anatomical_location": "On dorsum of foot, 1.5 cun distal to ST41, at highest point of foot arch",
    "healing_function": "Activates channel, alleviates pain",
    "martial_application": "Severe pain when stomped, disrupts grounding",
    "shared_name_indicator": null,
    "bilateral": "Yes"
  },
  {
    "meridian_name": "Stomach (ST)",
    "point_number": "ST43",
    "korean_name": "함곡",
    "romanized_korean": "Hahm Gok",
    "english_translation": "Striking Valley",
    "anatomical_location": "In depression distal to junction of 2nd and 3rd metatarsal bones",
    "healing_function": "Regulates intestines, clears edema",
    "martial_application": "Causes sharp pain and balance loss",
    "shared_name_indicator": null,
    "bilateral": "Yes"
  },
  {
    "meridian_name": "Stomach (ST)",
    "point_number": "ST44",
    "korean_name": "내정",
    "romanized_korean": "Nae Juhng",
    "english_translation": "Inner Courtyard",
    "anatomical_location": "Proximal to web margin between 2nd and 3rd toes",
    "healing_function": "Clears stomach heat, relieves toothache",
    "martial_application": "Sensitive area, can unbalance or shock body",
    "shared_name_indicator": null,
    "bilateral": "Yes"
  },
  {
    "meridian_name": "Stomach (ST)",
    "point_number": "ST45",
    "korean_name": "여태",
    "romanized_korean": "Yea Tae",
    "english_translation": "Strict Exchange",
    "anatomical_location": "Lateral side of 2nd toe, 0.1 cun posterior to corner of nail",
    "healing_function": "Clears heat, restores consciousness",
    "martial_application": "Used in revival techniques or emergency applications",
    "shared_name_indicator": null,
    "bilateral": "Yes"
  }
]