[
  {
    "meridian_name": "Triple Burner (TB)",
    "point_number": "TB1",
    "korean_name": "관충",
    "romanized_korean": "Gwahn Choong",
    "english_translation": "Gate’s Pouring",
    "anatomical_location": "Ulnar side of ring finger, 0.1 cun posterior to corner of nail.",
    "healing_function": "Clears upper Jiao heat and benefits ears and tongue.",
    "martial_application": "Striking can cause numbness or fainting.",
    "shared_name_indicator": null,
    "bilateral": "Yes"
  },
  {
    "meridian_name": "Triple Burner (TB)",
    "point_number": "TB2",
    "korean_name": "액문",
    "romanized_korean": "Aek Moon",
    "english_translation": "Fluid",
    "anatomical_location": "Distal to 4th metacarpophalangeal joint on dorsum of hand.",
    "healing_function": "Disperses wind and clears heat.",
    "martial_application": "Striking disrupts nerve flow in hand.",
    "shared_name_indicator": null,
    "bilateral": "Yes"
  },
  {
    "meridian_name": "Triple Burner (TB)",
    "point_number": "TB3",
    "korean_name": "중지",
    "romanized_korean": "Joong Juh",
    "english_translation": "Middle Island",
    "anatomical_location": "Proximal to 4th metacarpophalangeal joint on dorsum of hand.",
    "healing_function": "Clears heat, regulates Qi, benefits ears.",
    "martial_application": "Can numb hand or shock nervous system.",
    "shared_name_indicator": null,
    "bilateral": "Yes"
  },
  {
    "meridian_name": "Triple Burner (TB)",
    "point_number": "TB4",
    "korean_name": "양지",
    "romanized_korean": "Yahng Jee",
    "english_translation": "Pool of Yahng",
    "anatomical_location": "On wrist crease, between extensor digitorum and extensor digiti minimi.",
    "healing_function": "Yuan-source point; relaxes sinews and clears heat.",
    "martial_application": "Striking weakens grip and forearm.",
    "shared_name_indicator": null,
    "bilateral": "Yes"
  },
  {
    "meridian_name": "Triple Burner (TB)",
    "point_number": "TB5",
    "korean_name": "외관",
    "romanized_korean": "Oe Gwahn",
    "english_translation": "Outer Gate",
    "anatomical_location": "2 cun proximal to TB4, between radius and ulna.",
    "healing_function": "Expels wind, releases exterior, clears head.",
    "martial_application": "Can impair wrist or forearm movement.",
    "shared_name_indicator": null,
    "bilateral": "Yes"
  },
  {
    "meridian_name": "Triple Burner (TB)",
    "point_number": "TB6",
    "korean_name": "지구",
    "romanized_korean": "Jee Goo",
    "english_translation": "Branch Ditch",
    "anatomical_location": "3 cun proximal to TB4, between radius and ulna.",
    "healing_function": "Clears heat, benefits voice, relieves pain.",
    "martial_application": "Target for controlling arm Qi.",
    "shared_name_indicator": null,
    "bilateral": "Yes"
  },
  {
    "meridian_name": "Triple Burner (TB)",
    "point_number": "TB7",
    "korean_name": "회종",
    "romanized_korean": "Hoe Joong",
    "english_translation": "Meeting of the Clan",
    "anatomical_location": "4 cun proximal to TB4, between radius and ulna.",
    "healing_function": "Clears San Jiao channel, benefits hearing.",
    "martial_application": "Shock point for arm paralysis.",
    "shared_name_indicator": null,
    "bilateral": "Yes"
  },
  {
    "meridian_name": "Triple Burner (TB)",
    "point_number": "TB8",
    "korean_name": "삼양락",
    "romanized_korean": "Sahm Yahng Nahk",
    "english_translation": "Three Yahng Junction",
    "anatomical_location": "5 cun proximal to TB4, between radius and ulna.",
    "healing_function": "Clears head, relieves pain in shoulder and neck.",
    "martial_application": "Striking affects shoulder joint.",
    "shared_name_indicator": null,
    "bilateral": "Yes"
  },
  {
    "meridian_name": "Triple Burner (TB)",
    "point_number": "TB9",
    "korean_name": "사독",
    "romanized_korean": "Sah Dohk",
    "english_translation": "Four Ditch",
    "anatomical_location": "7 cun proximal to TB4, between radius and ulna.",
    "healing_function": "Clears heat, benefits throat and ears.",
    "martial_application": "Impacts arm function.",
    "shared_name_indicator": null,
    "bilateral": "Yes"
  },
  {
    "meridian_name": "Triple Burner (TB)",
    "point_number": "TB10",
    "korean_name": "천정",
    "romanized_korean": "Chuhn Juhng",
    "english_translation": "Celestial Well",
    "anatomical_location": "1 cun superior to olecranon, in depression.",
    "healing_function": "Clears heat, relaxes tendons, benefits shoulder.",
    "martial_application": "Can disable elbow joint.",
    "shared_name_indicator": null,
    "bilateral": "Yes"
  },
  {
    "meridian_name": "Triple Burner (TB)",
    "point_number": "TB11",
    "korean_name": "청랭연",
    "romanized_korean": "Chunhng Naeng",
    "english_translation": "Clear Cold Gulf",
    "anatomical_location": "1 cun superior to TB10, on line to acromion.",
    "healing_function": "Clears heat and transforms phlegm.",
    "martial_application": "Shock or spasm in triceps.",
    "shared_name_indicator": null,
    "bilateral": "Yes"
  },
  {
    "meridian_name": "Triple Burner (TB)",
    "point_number": "TB12",
    "korean_name": "소박",
    "romanized_korean": "Yuhn",
    "english_translation": "Dissipate the Damp",
    "anatomical_location": "Midway between TB11 and TB13, posterior arm.",
    "healing_function": "Relieves pain and benefits shoulder joint.",
    "martial_application": "Affects shoulder and triceps.",
    "shared_name_indicator": null,
    "bilateral": "Yes"
  },
  {
    "meridian_name": "Triple Burner (TB)",
    "point_number": "TB13",
    "korean_name": "뇌회",
    "romanized_korean": "Soh Bahk",
    "english_translation": "Shoulder’s Meeting",
    "anatomical_location": "Posterior arm, 3 cun below acromion.",
    "healing_function": "Regulates Qi and dissipates masses.",
    "martial_application": "Strike can weaken deltoid region.",
    "shared_name_indicator": null,
    "bilateral": "Yes"
  },
  {
    "meridian_name": "Triple Burner (TB)",
    "point_number": "TB14",
    "korean_name": "견료",
    "romanized_korean": "Nie Hoe",
    "english_translation": "Shoulder Seam",
    "anatomical_location": "In depression posterior and inferior to acromion.",
    "healing_function": "Benefits shoulder and dispels wind.",
    "martial_application": "Weakens arm lift, pain in shoulder.",
    "shared_name_indicator": null,
    "bilateral": "Yes"
  },
  {
    "meridian_name": "Triple Burner (TB)",
    "point_number": "TB15",
    "korean_name": "천료",
    "romanized_korean": "Kyuhl Lyoh",
    "english_translation": "Heaven’s Seam",
    "anatomical_location": "Posterior superior angle of scapula, near SI13.",
    "healing_function": "Activates channel and alleviates pain.",
    "martial_application": "Causes shoulder blade dysfunction.",
    "shared_name_indicator": null,
    "bilateral": "Yes"
  },
  {
    "meridian_name": "Triple Burner (TB)",
    "point_number": "TB16",
    "korean_name": "천유",
    "romanized_korean": "Chuhl Lyoh",
    "english_translation": "Heaven’s Window",
    "anatomical_location": "Midway between GB21 and SI13, posterior shoulder.",
    "healing_function": "Opens channel and relieves pain.",
    "martial_application": "Pain or dysfunction in shoulder joint.",
    "shared_name_indicator": null,
    "bilateral": "Yes"
  },
  {
    "meridian_name": "Triple Burner (TB)",
    "point_number": "TB17",
    "korean_name": "예풍",
    "romanized_korean": "Chuhn Yohng",
    "english_translation": "Sheltering Wind",
    "anatomical_location": "Posterior to ear lobe in depression between mandible and mastoid.",
    "healing_function": "Benefits ears, dispels wind.",
    "martial_application": "Sensitive point; stunning effect.",
    "shared_name_indicator": null,
    "bilateral": "Yes"
  },
  {
    "meridian_name": "Triple Burner (TB)",
    "point_number": "TB18",
    "korean_name": "계맥",
    "romanized_korean": "Yae Poong",
    "english_translation": "Feeding the Vessel",
    "anatomical_location": "1 cun posterior to TB17, behind earlobe.",
    "healing_function": "Clears head and benefits hearing.",
    "martial_application": "Can disorient or disturb balance.",
    "shared_name_indicator": null,
    "bilateral": "Yes"
  },
  {
    "meridian_name": "Triple Burner (TB)",
    "point_number": "TB19",
    "korean_name": "노식",
    "romanized_korean": "Gyea Maek",
    "english_translation": "Skull’s Rest",
    "anatomical_location": "Posterior to mastoid, level with root of auricle.",
    "healing_function": "Clears heat, relieves pain in neck and head.",
    "martial_application": "Target for disorienting strike.",
    "shared_name_indicator": null,
    "bilateral": "Yes"
  },
  {
    "meridian_name": "Triple Burner (TB)",
    "point_number": "TB20",
    "korean_name": "각손",
    "romanized_korean": "Noh Shik",
    "english_translation": "Angle of Regeneration",
    "anatomical_location": "At corner of forehead, posterior to GB6.",
    "healing_function": "Clears temples, benefits hearing and vision.",
    "martial_application": "Disrupts vision or orientation.",
    "shared_name_indicator": null,
    "bilateral": "Yes"
  },
  {
    "meridian_name": "Triple Burner (TB)",
    "point_number": "TB21",
    "korean_name": "이문",
    "romanized_korean": "Gahk Sohn",
    "english_translation": "Ear Gate",
    "anatomical_location": "Anterior to ear root, behind SI19.",
    "healing_function": "Benefits ears and jaw, relieves pain.",
    "martial_application": "Can shock or disable hearing.",
    "shared_name_indicator": null,
    "bilateral": "Yes"
  },
  {
    "meridian_name": "Triple Burner (TB)",
    "point_number": "TB22",
    "korean_name": "화료",
    "romanized_korean": "Ee Moon",
    "english_translation": "Harmony’s Seam",
    "anatomical_location": "Anterior to intertragic notch, posterior to condyloid process.",
    "healing_function": "Benefits ears and eliminates wind.",
    "martial_application": "Stunning point to ear/jaw area.",
    "shared_name_indicator": null,
    "bilateral": "Yes"
  },
  {
    "meridian_name": "Triple Burner (TB)",
    "point_number": "TB23",
    "korean_name": "사죽공",
    "romanized_korean": "Sah Jook Kohng",
    "english_translation": "Silken Bamboo Hollow",
    "anatomical_location": "At lateral end of eyebrow, in depression.",
    "healing_function": "Clears heat, benefits eyes and head.",
    "martial_application": "Target for disabling vision or shocking consciousness.",
    "shared_name_indicator": null,
    "bilateral": "Yes"
  }
]